{"apis_index.md":"d913c02e","component_account-input.md":"b6a89176","component_app-logo.md":"3abd201d","component_app-name.md":"86291b21","component_button.md":"1f69b530","component_element.md":"1ebc7020","component_error-text.md":"8bd3ef87","component_guard-container.md":"1d6f40e4","component_guard.md":"966b8216","component_image.md":"544b7244","component_index.md":"e0a8868c","component_input.md":"186b34c8","component_login-button.md":"2da14265","component_password-input.md":"7aeb530a","component_text.md":"9cd10937","guide_accent-color.md":"3258199b","guide_advanced-login.md":"5b22b858","guide_advanced-register.md":"7427266b","guide_background-image.md":"d75c113a","guide_case-study_coca-cola.md":"3c3604fa","guide_getting-started.md":"9f974103","guide_index.md":"0448af4d","guide_methods_change-language.md":"97d16140","guide_methods_check-login-status.md":"d93d6e84","guide_methods_get-guard-instance.md":"d87f86ef","guide_methods_get-user-info.md":"74764495","guide_methods_handle-events.md":"de64acc3","guide_methods_initialize.md":"e420feb4","guide_methods_logout.md":"be0fdaf1","guide_playground.md":"c8232f1d","guide_register.md":"4154fd77","guide_reset-password.md":"c0c3f478","guide_router.md":"e512c986","index.md":"f0643c2e"}
